tornado_botocore/__init__.py
tornado_botocore/base.py
tornado_botocore-1.5.0.dist-info/AUTHORS
tornado_botocore-1.5.0.dist-info/LICENSE
tornado_botocore-1.5.0.dist-info/METADATA
tornado_botocore-1.5.0.dist-info/WHEEL
tornado_botocore-1.5.0.dist-info/top_level.txt
tornado_botocore-1.5.0.dist-info/RECORD
