Metadata-Version: 1.0
Name: tornado-botocore
Version: 1.5.0
Summary: Use tornado's AsyncHTTPClient inside botocore.
